matsim.cpython-36m-darwin.so
matsim/matsim.cpython-36m-darwin.so
matsim-0.2.3.dist-info/LICENSE
matsim-0.2.3.dist-info/METADATA
matsim-0.2.3.dist-info/WHEEL
matsim-0.2.3.dist-info/top_level.txt
matsim-0.2.3.dist-info/RECORD
