Metadata-Version: 2.1
Name: matsim
Version: 0.2.3
Summary: Package primarily for simulation of MAT model
Home-page: UNKNOWN
Author: Tomas Barta
Author-email: tomas.barta@fgu.cas.cz
License: UNKNOWN
Platform: UNKNOWN
